src/design/mostrar_lcd.sv
// FSM interna de 4 estados (IDLE/HOME/SEND/WAIT) de docs/M04_Mostrar-LCD.md, fusionada con la
// arquitectura de nivel03: no hay "show" desde la FSM principal, este modulo decodifica "state"
// y repinta solo cuando cambia lo que le corresponde mostrar (state, modo en SELECCION, mascara
// en JUEGO). letra_in se elimino del puerto: para redibujar la palabra completa con varias
// letras ya reveladas hace falta la palabra secreta entera, no solo la ultima letra recibida,
// asi que word/word_length se agregaron desde REG_Palabra-escogida (mismo origen que M07 y M11).
module mostrar_lcd (
  input logic        clk,
  input logic        rst,

  input logic [2:0]  i_state,        // desde M13_FSM, decide cual pantalla toca
  input logic        i_modo,         // desde M13_FSM, 0=FACIL 1=DIFICIL
  input logic [7:0]  i_word [0:11],  // palabra escogida, desde REG_Palabra-escogida
  input logic [3:0]  i_word_length,  // cuantas posiciones de i_word son validas
  input logic [11:0] i_mascara,      // posiciones ya reveladas, desde M07_Comparador-letra

  input logic [31:0] i_rdata,        // lo que devuelve PERIFERICO_LCD en la direccion que le estoy poniendo

  output logic [1:0]  o_addr,
  output logic        o_write_enable,
  output logic [31:0] o_wdata
  );

  // TODO: Revisar ADDR_CTRL_ESTADO/ADDR_DATOS con el frente de LCD, el enunciado no fija estas direcciones
  localparam logic [1:0] ADDR_CTRL_ESTADO = 2'b00;
  localparam logic [1:0] ADDR_DATOS       = 2'b01;

  localparam BIT_START = 0;
  localparam BIT_RS    = 1;
  localparam BIT_CLEAR = 2;
  localparam BIT_HOME  = 3;
  localparam BIT_DONE  = 9;

  // Codificacion de state, fijada por fsm.sv. PERDIO_INTENTOS y PERDIO_TIEMPO se unificaron en
  // un solo ST_PERDIO, ya no hay forma de distinguir la causa desde state.
  localparam logic [2:0] ST_SELECCION = 3'b000;
  localparam logic [2:0] ST_CARGA     = 3'b001;
  localparam logic [2:0] ST_JUEGO     = 3'b010;
  localparam logic [2:0] ST_GANO      = 3'b011;
  localparam logic [2:0] ST_PERDIO    = 3'b100;

  // FSM interna, codificacion fija por diseño (S1 S0): IDLE=00, HOME=01, SEND=10, WAIT=11
  localparam logic [1:0] IDLE = 2'b00;
  localparam logic [1:0] HOME = 2'b01;
  localparam logic [1:0] SEND = 2'b10;
  localparam logic [1:0] WAIT = 2'b11;

  logic [1:0] estado, estado_siguiente;
  // Dentro de SEND: 0 escribe el byte en REG_DATOS, 1 pulsa start/rs en REG_CTRL_ESTADO.
  // Son dos direcciones distintas del mismo bus, no caben en el mismo ciclo.
  logic byte_step, byte_step_siguiente;
  logic [3:0] pos, pos_siguiente; // CONT_POSICION, direccion dentro del mensaje

  // Contenido "activo": foto de lo que se esta enviando, tomada al entrar a HOME, para no
  // mezclar dos mensajes distintos si el contenido cambia a medio envio.
  logic [2:0]  act_state;
  logic        act_modo;
  logic [11:0] act_mascara;
  logic [3:0]  act_last_pos; // ultima posicion valida del mensaje activo (largo - 1)

  function automatic logic [7:0] f_byte(
      input logic [2:0] st,
      input logic       mo,
      input logic [3:0] p
    );
    logic [7:0] b;
    begin
      b = " ";
      case (st)
        ST_SELECCION: begin
          if (mo) begin // "MODO: DIFICIL", 13 caracteres
            case (p)
              4'd0: b = "M"; 4'd1: b = "O"; 4'd2: b = "D"; 4'd3:  b = "O"; 4'd4:  b = ":";
              4'd5: b = " "; 4'd6: b = "D"; 4'd7: b = "I"; 4'd8:  b = "F"; 4'd9:  b = "I";
              4'd10: b = "C"; 4'd11: b = "I"; 4'd12: b = "L";
              default: b = " ";
            endcase
          end
          else begin // "MODO: FACIL", 11 caracteres
            case (p)
              4'd0: b = "M"; 4'd1: b = "O"; 4'd2: b = "D"; 4'd3: b = "O"; 4'd4: b = ":";
              4'd5: b = " "; 4'd6: b = "F"; 4'd7: b = "A"; 4'd8: b = "C"; 4'd9: b = "I";
              4'd10: b = "L";
              default: b = " ";
            endcase
          end
        end
        ST_GANO: begin // "GANASTE", 7 caracteres
          case (p)
            4'd0: b = "G"; 4'd1: b = "A"; 4'd2: b = "N"; 4'd3: b = "A"; 4'd4: b = "S";
            4'd5: b = "T"; 4'd6: b = "E";
            default: b = " ";
          endcase
        end
        ST_PERDIO: begin // "PERDISTE", 8 caracteres, sin causa porque state ya no la distingue
          case (p)
            4'd0: b = "P"; 4'd1: b = "E"; 4'd2: b = "R"; 4'd3: b = "D";
            4'd4: b = "I"; 4'd5: b = "S"; 4'd6: b = "T"; 4'd7: b = "E";
            default: b = " ";
          endcase
        end
        default: b = " "; // SELECCION/CARGA sin pantalla asignada aqui no llegan a f_byte
      endcase
      f_byte = b;
    end
  endfunction

  // Largo (ultima posicion) de cada mensaje, se calcula una sola vez al entrar a HOME
  function automatic logic [3:0] f_last_pos(input logic [2:0] st, input logic mo, input logic [3:0] wlen);
    case (st)
      ST_SELECCION: f_last_pos = mo ? 4'd12 : 4'd10;
      ST_JUEGO:     f_last_pos = (wlen == 4'd0) ? 4'd0 : (wlen - 4'd1);
      ST_GANO:      f_last_pos = 4'd6;
      ST_PERDIO:    f_last_pos = 4'd7;
      default:      f_last_pos = 4'd0;
    endcase
  endfunction

  logic done;
  assign done = i_rdata[BIT_DONE];

  // "cambio" reemplaza al pulso show que tenia la FSM principal: se repinta cuando cambia el
  // state, o cuando cambia lo que compone la pantalla actual (modo en SELECCION, mascara en
  // JUEGO). Se compara contra la foto "activa", asi que si el contenido cambia otra vez a medio
  // envio, cambio se mantiene en 1 y en cuanto vuelve a IDLE arranca un nuevo envio con lo mas
  // reciente.
  logic cambio;
  assign cambio = (i_state != act_state)
                || (i_state == ST_SELECCION && i_modo    != act_modo)
                || (i_state == ST_JUEGO     && i_mascara != act_mascara);

  always_comb begin
    estado_siguiente    = estado;
    byte_step_siguiente = byte_step;
    pos_siguiente        = pos;

    case (estado)
      // CARGA no tiene pantalla propia (M04_Mostrar-LCD.md g), no dispara redibujado
      IDLE: if (cambio && i_state != ST_CARGA) begin
              estado_siguiente    = HOME;
              pos_siguiente       = 4'd0;
              byte_step_siguiente = 1'b0;
            end
      // Mismo truco de sub-paso que SEND: byte_step=0 emite home/clear, byte_step=1 espera done
      // antes de pasar a SEND. HOME no puede avanzar sin esperar done: el HD44780 tarda mucho
      // mas en un clear/home que en una escritura normal, y sin esta espera el primer byte del
      // mensaje se pisa con el propio home/clear (visto en simulacion con tb_mostrar_lcd.sv).
      HOME: if (byte_step == 1'b0)
              byte_step_siguiente = 1'b1;
            else if (done) begin
              estado_siguiente    = SEND;
              byte_step_siguiente = 1'b0;
            end
      SEND: if (byte_step == 1'b0)
              byte_step_siguiente = 1'b1;
            else begin
              estado_siguiente    = WAIT;
              byte_step_siguiente = 1'b0;
            end
      WAIT: if (done) begin
              if (pos == act_last_pos)
                estado_siguiente = IDLE;
              else begin
                estado_siguiente = SEND;
                pos_siguiente    = pos + 4'd1;
              end
            end
    endcase
  end

  always_ff @(posedge clk) begin
    if (rst) begin
      estado       <= IDLE;
      byte_step    <= 1'b0;
      pos          <= 4'd0;
      act_state    <= 3'b111; // codigo no usado por M13_FSM, fuerza el primer redibujado
      act_modo     <= 1'b0;
      act_mascara  <= 12'b0;
      act_last_pos <= 4'd0;
    end
    else begin
      estado    <= estado_siguiente;
      byte_step <= byte_step_siguiente;
      pos       <= pos_siguiente;
      // Foto del contenido, tomada justo al arrancar el envio (IDLE -> HOME)
      if (estado == IDLE && estado_siguiente == HOME) begin
        act_state    <= i_state;
        act_modo     <= i_modo;
        act_mascara  <= i_mascara;
        act_last_pos <= f_last_pos(i_state, i_modo, i_word_length);
      end
    end
  end

  always_comb begin
    o_addr         = ADDR_CTRL_ESTADO;
    o_write_enable = 1'b0;
    o_wdata        = 32'b0;
    case (estado)
      // home + clear en el mismo golpe: home posiciona el cursor, clear borra lo que haya
      // quedado de un mensaje anterior mas largo que el nuevo. Solo se escribe una vez
      // (byte_step==0); mientras byte_step==1 el modulo solo esta esperando done, sin volver
      // a pulsar el comando.
      HOME: if (byte_step == 1'b0) begin
              o_write_enable      = 1'b1;
              o_wdata[BIT_CLEAR]  = 1'b1;
              o_wdata[BIT_HOME]   = 1'b1;
            end
      SEND: if (byte_step == 1'b0) begin
              o_addr         = ADDR_DATOS;
              o_write_enable = 1'b1;
              // Posiciones reveladas muestran la letra real de la palabra, el resto un guion bajo
              o_wdata[7:0]   = (act_state == ST_JUEGO) ? (act_mascara[pos] ? i_word[pos] : "_")
                                                        : f_byte(act_state, act_modo, pos);
            end
            else begin
              o_write_enable     = 1'b1;
              o_wdata[BIT_START] = 1'b1;
              o_wdata[BIT_RS]    = 1'b1; // dato, no comando
            end
    endcase
  end

endmodule

src/sim/tb_mostrar_lcd.sv
`timescale 1ns/1ps

// Testbench de mostrar_lcd. Corre con: make sim TB=mostrar_lcd (o make wave TB=mostrar_lcd)
//
// M13_FSM y PERIFERICO_LCD todavia no existen como .sv en el repo (solo en los documentos de
// diseño), asi que este testbench hace de las dos cosas a la vez: maneja i_state/i_modo como si
// fuera la FSM principal, y modela PERIFERICO_LCD con un stub de comportamiento (registro de
// pantalla de 16 caracteres + temporizador de busy/done) para poder verificar en simulacion que
// mostrar_lcd arma y manda los mensajes correctos, no solo que compila.
//
// El stub es deliberadamente permisivo con el hueco ya documentado en
// docs/diseño/modulos/M04_Mostrar-LCD.md h): HOME pasa a SEND sin esperar el done del propio
// home/clear. Si un PERIFERICO_LCD real tarda mas en ese comando que en una escritura normal,
// el primer byte del mensaje podria perderse ahi; este stub solo lo señala con un $display, no
// lo hace fallar, porque arreglarlo es un cambio de la tabla de estados documentada, no de este
// testbench (ver el aviso en la respuesta que acompaña este archivo).
//
// Nota de estilo, igual que en tb_temporizador.sv: las comprobaciones se escriben como macros
// (`define), no como task/function, porque en Icarus Verilog una llamada a tarea/funcion dentro
// del bloque initial corrompe el siguiente @(posedge clk) del mismo proceso.
module tb_mostrar_lcd;

  // Codificacion de state, igual que M13_FSM y que mostrar_lcd.sv
  localparam logic [2:0] ST_SELECCION       = 3'b000;
  localparam logic [2:0] ST_CARGA           = 3'b001;
  localparam logic [2:0] ST_JUEGO           = 3'b010;
  localparam logic [2:0] ST_GANO            = 3'b011;
  localparam logic [2:0] ST_PERDIO = 3'b100;

  // Codificacion de la FSM interna de mostrar_lcd, para poder esperar por hierarchical ref
  // (dut.estado), igual que tb_temporizador.sv usa dut.running.
  localparam logic [1:0] IDLE_ENC = 2'b00;
  localparam logic [1:0] HOME_ENC = 2'b01;
  localparam logic [1:0] SEND_ENC = 2'b10;
  localparam logic [1:0] WAIT_ENC = 2'b11;

  // Direcciones y bits del bus, deben coincidir con los localparam de mostrar_lcd.sv: este
  // stub hace las veces de PERIFERICO_LCD, asi que tiene que hablar el mismo contrato de bus.
  localparam logic [1:0] ADDR_CTRL_ESTADO = 2'b00;
  localparam logic [1:0] ADDR_DATOS       = 2'b01;
  localparam BIT_START = 0;
  localparam BIT_RS    = 1;
  localparam BIT_CLEAR = 2;
  localparam BIT_HOME  = 3;
  localparam BIT_BUSY  = 8;
  localparam BIT_DONE  = 9;

  localparam int BUSY_CYCLES_DATO = 2; // ciclos de "busy" simulados para start/rs
  localparam int BUSY_CYCLES_HOME = 4; // ciclos de "busy" simulados para clear/home (mas largo en HW real)

  logic clk;
  logic rst;

  logic [2:0]  i_state;
  logic        i_modo;
  logic [7:0]  i_word [0:11];
  logic [3:0]  i_word_length;
  logic [11:0] i_mascara;
  logic [31:0] i_rdata;

  logic [1:0]  o_addr;
  logic        o_write_enable;
  logic [31:0] o_wdata;

  int errores = 0;

  mostrar_lcd dut (
    .clk(clk),
    .rst(rst),
    .i_state(i_state),
    .i_modo(i_modo),
    .i_word(i_word),
    .i_word_length(i_word_length),
    .i_mascara(i_mascara),
    .i_rdata(i_rdata),
    .o_addr(o_addr),
    .o_write_enable(o_write_enable),
    .o_wdata(o_wdata)
  );

  initial clk = 1'b0;
  always #5 clk = ~clk;

  // ------------------------------------------------------------------
  // Stub de PERIFERICO_LCD: registro de pantalla de 16 caracteres, cursor que auto-incrementa
  // con cada byte de datos (como el DDRAM del HD44780 en modo de incremento), y un temporizador
  // que retrasa "done" unos ciclos para forzar a mostrar_lcd a sondear WAIT de verdad, no solo
  // ver done=1 de inmediato.
  // ------------------------------------------------------------------
  logic [7:0] screen [0:15];
  logic [3:0] cursor;
  logic [7:0] pending_byte;
  logic       busy, done;
  logic       timer_activo;
  int         timer;

  assign i_rdata = {22'b0, done, busy, 8'b0};

  always_ff @(posedge clk) begin
    if (rst) begin
      cursor       <= 4'd0;
      pending_byte <= 8'h00;
      busy         <= 1'b0;
      done         <= 1'b0;
      timer_activo <= 1'b0;
      for (int i = 0; i < 16; i = i + 1) screen[i] <= " ";
    end
    else begin
      done <= 1'b0; // done es un pulso de un ciclo

      if (timer_activo) begin
        if (timer == 0) begin
          busy         <= 1'b0;
          done         <= 1'b1;
          timer_activo <= 1'b0;
        end
        else timer <= timer - 1;
        // Aviso (no falla la prueba) del hueco documentado: HOME->SEND sin esperar done propio
        if (o_write_enable)
          $display("NOTA  [%0t ns] el stub seguia \"busy\" (home/clear o dato anterior) cuando mostrar_lcd ya escribio de nuevo (addr=%0d)", $time, o_addr);
      end
      else if (o_write_enable && o_addr == ADDR_CTRL_ESTADO && (o_wdata[BIT_CLEAR] || o_wdata[BIT_HOME])) begin
        for (int i = 0; i < 16; i = i + 1) screen[i] <= " ";
        cursor       <= 4'd0;
        busy         <= 1'b1;
        timer        <= BUSY_CYCLES_HOME;
        timer_activo <= 1'b1;
      end
      else if (o_write_enable && o_addr == ADDR_CTRL_ESTADO && o_wdata[BIT_START]) begin
        if (o_wdata[BIT_RS]) begin // dato: se escribe en la pantalla y el cursor avanza
          screen[cursor] <= pending_byte;
          cursor         <= cursor + 4'd1;
        end
        busy         <= 1'b1;
        timer        <= BUSY_CYCLES_DATO;
        timer_activo <= 1'b1;
      end
      else if (o_write_enable && o_addr == ADDR_DATOS) begin
        pending_byte <= o_wdata[7:0];
      end
    end
  end

  // Watchdog: si algo se queda esperando una transicion que no llega (p.ej. un "wait" mal
  // planteado, como el que causo el cuelgue original de este archivo), corta la simulacion en
  // vez de dejarla correr para siempre. 20000 ciclos de sobra para las 11 pruebas de abajo.
  initial begin
    repeat (20000) @(posedge clk);
    $display("FALLO: WATCHDOG, la simulacion no termino a tiempo (posible deadlock)");
    errores = errores + 1;
    $finish;
  end

  // ------------------------------------------------------------------
  // Macros de comprobacion (ver nota de estilo arriba)
  // ------------------------------------------------------------------
  `define CHECK_BIT(nombre, got, expected) \
      if ((got) !== (expected)) begin \
          $display("FALLO [%0t ns] %s: se esperaba %0b, se obtuvo %0b", $time, nombre, (expected), (got)); \
          errores = errores + 1; \
      end else begin \
          $display("OK    [%0t ns] %s: %0b", $time, nombre, (got)); \
      end

  // Compara screen[0..len-1] contra texto (literal de Verilog) y screen[len..15] contra espacios
  `define CHECK_SCREEN(nombre, texto, len) \
      begin \
          logic [8*(len)-1:0] __ref; \
          string __got; \
          logic  __ok; \
          __ref = texto; \
          __got = ""; \
          __ok  = 1'b1; \
          for (int __i = 0; __i < 16; __i = __i + 1) begin \
              __got = {__got, string'(screen[__i])}; \
              if (__i < (len)) begin \
                  if (screen[__i] !== __ref[8*((len)-1-__i) +: 8]) __ok = 1'b0; \
              end else begin \
                  if (screen[__i] !== " ") __ok = 1'b0; \
              end \
          end \
          if (__ok) $display("OK    [%0t ns] %s: pantalla=\"%s\"", $time, nombre, __got); \
          else begin \
              $display("FALLO [%0t ns] %s: pantalla=\"%s\", se esperaba \"%s\" (relleno con espacios)", $time, nombre, __got, texto); \
              errores = errores + 1; \
          end \
      end

  // Espera lo suficiente para que termine cualquier redibujado pendiente. No cazamos el flanco
  // IDLE->HOME con "wait": mostrar_lcd puede arrancar su redibujado en el mismo ciclo en que se
  // suelta rst (no espera ningun pulso externo), asi que un "wait(dut.estado==HOME_ENC)" puede
  // arrancar despues de que esa transicion ya paso, y quedarse esperando para siempre una que no
  // vuelve a ocurrir. El peor caso real (mensaje de 16 caracteres, con el primer byte pisado por
  // el propio home/clear, ver el aviso de mas arriba) tarda del orden de 100 ciclos; 150 de
  // margen alcanza siempre.
  `define WAIT_REDIBUJADO repeat (150) @(posedge clk); #1;

  initial begin
    $dumpfile("tb_mostrar_lcd.vcd");
    $dumpvars(0, tb_mostrar_lcd);

    rst           = 1'b1;
    i_state       = ST_SELECCION;
    i_modo        = 1'b0;
    i_mascara     = 12'b0;
    i_word_length = 4'd0;
    for (int k = 0; k < 12; k = k + 1) i_word[k] = " ";
    repeat (3) @(posedge clk);
    rst = 1'b0;

    // No hay una comprobacion de "sigue en IDLE justo despues del reset": el redibujado arranca
    // solo, sin ningun pulso "show" externo (la sola diferencia entre state/modo actuales y la
    // foto activa, que arranca invalida a proposito, ya dispara el primer redibujado), y puede
    // arrancar en el mismo ciclo en que se suelta rst. Lo que importa es el resultado.
    `WAIT_REDIBUJADO
    `CHECK_SCREEN("seleccion FACIL", "MODO: FACIL", 11)

    // 2) sel conmuta el modo (M09/M13_FSM ya resuelto): M04 lo ve como un cambio de modo y
    //    redibuja solo, sin que nadie se lo ordene.
    i_modo = 1'b1;
    `WAIT_REDIBUJADO
    `CHECK_SCREEN("seleccion DIFICIL", "MODO: DIFICIL", 13)

    // 3) CARGA no tiene pantalla propia: no debe disparar redibujado ni tocar el bus
    i_state = ST_CARGA;
    repeat (5) @(posedge clk);
    `CHECK_BIT("CARGA: no dispara redibujado", dut.estado, IDLE_ENC)
    `CHECK_SCREEN("CARGA: la pantalla se mantiene (DIFICIL)", "MODO: DIFICIL", 13)

    // 4) Entra a JUEGO con la palabra "GATO", nada revelado todavia (mascara = 0, como la deja
    //    M07_Comparador-letra recien limpiada en CARGA)
    i_word[0] = "G"; i_word[1] = "A"; i_word[2] = "T"; i_word[3] = "O";
    i_word_length = 4'd4;
    i_mascara     = 12'b0000_0000_0000;
    i_state       = ST_JUEGO;
    `WAIT_REDIBUJADO
    `CHECK_SCREEN("juego: nada revelado", "____", 4)

    // 5) M07 revela la G (posicion 0): mascara cambia, M04 redibuja solo
    i_mascara = 12'b0000_0000_0001;
    `WAIT_REDIBUJADO
    `CHECK_SCREEN("juego: G revelada", "G___", 4)

    // 6) Se revela tambien la T (posicion 2), sin perder la G ya pintada
    i_mascara = 12'b0000_0000_0101;
    `WAIT_REDIBUJADO
    `CHECK_SCREEN("juego: G y T reveladas", "G_T_", 4)

    // 7) Se revela la A: dispara un nuevo redibujado ("GAT_"). A medio camino de ESE redibujado
    //    se revela tambien la O (palabra completa). Verifica que "cambio" se mantenga en 1
    //    durante toda la rafaga en curso y que, al volver a IDLE, arranque sola una segunda
    //    rafaga con el contenido mas reciente -- sin quedar nunca una pantalla a medias.
    i_mascara = 12'b0000_0000_0111; // + A revelada, dispara el redibujado que arranca con "GAT_"
    wait (dut.estado == HOME_ENC);  // confirma que arranco esa primera rafaga
    i_mascara = 12'b0000_0000_1111; // + O revelada, a medio camino de la rafaga que ya arranco
    wait (dut.estado == IDLE_ENC);  // termina esa primera rafaga (arrancada con la foto "GAT_")
    @(posedge clk);                 // deja que "cambio" se evalue con la mascara mas nueva
    wait (dut.estado == HOME_ENC);  // arranca sola una segunda rafaga
    wait (dut.estado == IDLE_ENC);
    #1;
    `CHECK_SCREEN("juego: redibujado se actualiza aunque cambie a medio envio", "GATO", 4)

    // 8) Resultado: GANO
    i_state = ST_GANO;
    `WAIT_REDIBUJADO
    `CHECK_SCREEN("resultado: gano", "GANASTE", 7)

    // 9) Resultado: PERDIO (intentos y tiempo comparten un solo estado, sin causa distinguible)
    i_state = ST_PERDIO;
    `WAIT_REDIBUJADO
    `CHECK_SCREEN("resultado: perdio", "PERDISTE", 8)

    // 11) fin_espera: la FSM vuelve sola a SELECCION para la siguiente partida
    i_state = ST_SELECCION;
    i_modo  = 1'b0;
    `WAIT_REDIBUJADO
    `CHECK_SCREEN("vuelta a seleccion FACIL", "MODO: FACIL", 11)

    if (errores == 0)
        $display("\n=== TODAS LAS PRUEBAS PASARON ===");
    else
        $display("\n=== %0d PRUEBA(S) FALLARON ===", errores);

    $finish;
  end

endmodule

tb_mostrar_lcd.vcd
$date
	Thu Sep 10 13:49:48 2026
$end
$version
	Icarus Verilog
$end
$timescale
	1ps
$end
$scope module tb_mostrar_lcd $end
$var wire 1 ! o_write_enable $end
$var wire 32 " o_wdata [31:0] $end
$var wire 2 # o_addr [1:0] $end
$var wire 32 $ i_rdata [31:0] $end
$var parameter 2 % ADDR_CTRL_ESTADO $end
$var parameter 2 & ADDR_DATOS $end
$var parameter 32 ' BIT_BUSY $end
$var parameter 32 ( BIT_CLEAR $end
$var parameter 32 ) BIT_DONE $end
$var parameter 32 * BIT_HOME $end
$var parameter 32 + BIT_RS $end
$var parameter 32 , BIT_START $end
$var parameter 32 - BUSY_CYCLES_DATO $end
$var parameter 32 . BUSY_CYCLES_HOME $end
$var parameter 2 / HOME_ENC $end
$var parameter 2 0 IDLE_ENC $end
$var parameter 2 1 SEND_ENC $end
$var parameter 3 2 ST_CARGA $end
$var parameter 3 3 ST_GANO $end
$var parameter 3 4 ST_JUEGO $end
$var parameter 3 5 ST_PERDIO $end
$var parameter 3 6 ST_SELECCION $end
$var parameter 2 7 WAIT_ENC $end
$var reg 1 8 busy $end
$var reg 1 9 clk $end
$var reg 4 : cursor [3:0] $end
$var reg 1 ; done $end
$var reg 12 < i_mascara [11:0] $end
$var reg 1 = i_modo $end
$var reg 3 > i_state [2:0] $end
$var reg 4 ? i_word_length [3:0] $end
$var reg 8 @ pending_byte [7:0] $end
$var reg 1 A rst $end
$var reg 1 B timer_activo $end
$var integer 32 C errores [31:0] $end
$var integer 32 D timer [31:0] $end
$scope module dut $end
$var wire 1 E cambio $end
$var wire 1 9 clk $end
$var wire 12 F i_mascara [11:0] $end
$var wire 1 = i_modo $end
$var wire 32 G i_rdata [31:0] $end
$var wire 3 H i_state [2:0] $end
$var wire 4 I i_word_length [3:0] $end
$var wire 1 A rst $end
$var wire 1 J done $end
$var parameter 2 K ADDR_CTRL_ESTADO $end
$var parameter 2 L ADDR_DATOS $end
$var parameter 32 M BIT_CLEAR $end
$var parameter 32 N BIT_DONE $end
$var parameter 32 O BIT_HOME $end
$var parameter 32 P BIT_RS $end
$var parameter 32 Q BIT_START $end
$var parameter 2 R HOME $end
$var parameter 2 S IDLE $end
$var parameter 2 T SEND $end
$var parameter 3 U ST_CARGA $end
$var parameter 3 V ST_GANO $end
$var parameter 3 W ST_JUEGO $end
$var parameter 3 X ST_PERDIO $end
$var parameter 3 Y ST_SELECCION $end
$var parameter 2 Z WAIT $end
$var reg 4 [ act_last_pos [3:0] $end
$var reg 12 \ act_mascara [11:0] $end
$var reg 1 ] act_modo $end
$var reg 3 ^ act_state [2:0] $end
$var reg 1 _ byte_step $end
$var reg 1 ` byte_step_siguiente $end
$var reg 2 a estado [1:0] $end
$var reg 2 b estado_siguiente [1:0] $end
$var reg 2 c o_addr [1:0] $end
$var reg 32 d o_wdata [31:0] $end
$var reg 1 ! o_write_enable $end
$var reg 4 e pos [3:0] $end
$var reg 4 f pos_siguiente [3:0] $end
$scope function f_byte $end
$upscope $end
$scope function f_last_pos $end
$upscope $end
$upscope $end
$scope begin $ivl_for_loop0 $end
$var integer 32 g i [31:0] $end
$upscope $end
$scope begin $ivl_for_loop1 $end
$var integer 32 h i [31:0] $end
$upscope $end
$scope begin $ivl_for_loop2 $end
$var integer 32 i k [31:0] $end
$upscope $end
$scope begin $unm_blk_32 $end
$var reg 1 j __ok $end
$var reg 88 k __ref [87:0] $end
$scope begin $ivl_for_loop3 $end
$var integer 32 l __i [31:0] $end
$upscope $end
$upscope $end
$scope begin $unm_blk_37 $end
$var reg 1 m __ok $end
$var reg 104 n __ref [103:0] $end
$scope begin $ivl_for_loop4 $end
$var integer 32 o __i [31:0] $end
$upscope $end
$upscope $end
$scope begin $unm_blk_44 $end
$var reg 1 p __ok $end
$var reg 104 q __ref [103:0] $end
$scope begin $ivl_for_loop5 $end
$var integer 32 r __i [31:0] $end
$upscope $end
$upscope $end
$scope begin $unm_blk_49 $end
$var reg 1 s __ok $end
$var reg 32 t __ref [31:0] $end
$scope begin $ivl_for_loop6 $end
$var integer 32 u __i [31:0] $end
$upscope $end
$upscope $end
$scope begin $unm_blk_54 $end
$var reg 1 v __ok $end
$var reg 32 w __ref [31:0] $end
$scope begin $ivl_for_loop7 $end
$var integer 32 x __i [31:0] $end
$upscope $end
$upscope $end
$scope begin $unm_blk_59 $end
$var reg 1 y __ok $end
$var reg 32 z __ref [31:0] $end
$scope begin $ivl_for_loop8 $end
$var integer 32 { __i [31:0] $end
$upscope $end
$upscope $end
$scope begin $unm_blk_64 $end
$var reg 1 | __ok $end
$var reg 32 } __ref [31:0] $end
$scope begin $ivl_for_loop9 $end
$var integer 32 ~ __i [31:0] $end
$upscope $end
$upscope $end
$scope begin $unm_blk_69 $end
$var reg 1 !" __ok $end
$var reg 56 "" __ref [55:0] $end
$scope begin $ivl_for_loop10 $end
$var integer 32 #" __i [31:0] $end
$upscope $end
$upscope $end
$scope begin $unm_blk_74 $end
$var reg 1 $" __ok $end
$var reg 64 %" __ref [63:0] $end
$scope begin $ivl_for_loop11 $end
$var integer 32 &" __i [31:0] $end
$upscope $end
$upscope $end
$scope begin $unm_blk_79 $end
$var reg 1 '" __ok $end
$var reg 88 (" __ref [87:0] $end
$scope begin $ivl_for_loop12 $end
$var integer 32 )" __i [31:0] $end
$upscope $end
$upscope $end
$upscope $end
$enddefinitions $end
$comment Show the parameter values. $end
$dumpall
b11 Z
b0 Y
b100 X
b10 W
b11 V
b1 U
b10 T
b0 S
b1 R
b0 Q
b1 P
b11 O
b1001 N
b10 M
b1 L
b0 K
b11 7
b0 6
b100 5
b10 4
b11 3
b1 2
b10 1
b0 0
b1 /
b100 .
b10 -
b0 ,
b1 +
b11 *
b1001 )
b10 (
b1000 '
b1 &
b0 %
$end
#0
$dumpvars
b0 )"
bx ("
x'"
b0 &"
bx %"
x$"
b0 #"
bx ""
x!"
b0 ~
bx }
x|
b0 {
bx z
xy
b0 x
bx w
xv
b0 u
bx t
xs
b0 r
bx q
xp
b0 o
bx n
xm
b0 l
bx k
xj
b1100 i
b0 h
b0 g
bx f
bx e
b0 d
b0 c
bx b
bx a
x`
x_
bx ^
x]
bx \
bx [
xJ
b0 I
b0 H
b0xx00000000 G
b0 F
xE
b0 D
b0 C
xB
1A
bx @
b0 ?
b0 >
0=
b0 <
x;
bx :
09
x8
b0xx00000000 $
b0 #
b0 "
0!
$end
#5000
1E
b0 f
0`
b1 b
0J
b0 [
b0 \
0]
b111 ^
b0 e
0_
b0 a
0B
0;
b0 $
b0 G
08
b0 @
b0 :
b10000 g
19
#10000
09
#15000
b10000 g
19
#20000
09
#25000
0E
b1100 "
b1100 d
1!
1`
b1010 [
b0 ^
b1 a
b10000 g
0A
19
#30000
09
#35000
b0 "
b0 d
0!
1B
b100 D
b100000000 $
b100000000 G
18
1_
b10000 h
19
#40000
09
#45000
b11 D
19
#50000
09
#55000
b10 D
19
#60000
09
#65000
b1 D
19
#70000
09
#75000
b0 D
19
#80000
09
#85000
0`
b10 b
1J
0B
1;
b1000000000 $
b1000000000 G
08
19
#90000
09
#95000
0J
b1001101 "
b1001101 d
1!
b1 #
b1 c
1`
b0 $
b0 G
0;
0_
b10 a
19
#100000
09
#105000
b11 "
b11 d
1!
b0 #
b0 c
0`
b11 b
1_
b1001101 @
19
#110000
09
#115000
b0 "
b0 d
0!
1B
b10 D
b100000000 $
b100000000 G
18
b1 :
0_
b11 a
19
#120000
09
#125000
b1 D
19
#130000
09
#135000
b0 D
19
#140000
09
#145000
b1 f
b10 b
1J
0B
1;
b1000000000 $
b1000000000 G
08
19
#150000
09
#155000
0J
b1001111 "
b1001111 d
1!
b1 #
b1 c
1`
b0 $
b0 G
0;
b1 e
b10 a
19
#160000
09
#165000
b11 "
b11 d
1!
b0 #
b0 c
0`
b11 b
1_
b1001111 @
19
#170000
09
#175000
b0 "
b0 d
0!
1B
b10 D
b100000000 $
b100000000 G
18
b10 :
0_
b11 a
19
#180000
09
#185000
b1 D
19
#190000
09
#195000
b0 D
19
#200000
09
#205000
b10 f
b10 b
1J
0B
1;
b1000000000 $
b1000000000 G
08
19
#210000
09
#215000
0J
b1000100 "
b1000100 d
1!
b1 #
b1 c
1`
b0 $
b0 G
0;
b10 e
b10 a
19
#220000
09
#225000
b11 "
b11 d
1!
b0 #
b0 c
0`
b11 b
1_
b1000100 @
19
#230000
09
#235000
b0 "
b0 d
0!
1B
b10 D
b100000000 $
b100000000 G
18
b11 :
0_
b11 a
19
#240000
09
#245000
b1 D
19
#250000
09
#255000
b0 D
19
#260000
09
#265000
b11 f
b10 b
1J
0B
1;
b1000000000 $
b1000000000 G
08
19
#270000
09
#275000
0J
b1001111 "
b1001111 d
1!
b1 #
b1 c
1`
b0 $
b0 G
0;
b11 e
b10 a
19
#280000
09
#285000
b11 "
b11 d
1!
b0 #
b0 c
0`
b11 b
1_
b1001111 @
19
#290000
09
#295000
b0 "
b0 d
0!
1B
b10 D
b100000000 $
b100000000 G
18
b100 :
0_
b11 a
19
#300000
09
#305000
b1 D
19
#310000
09
#315000
b0 D
19
#320000
09
#325000
b100 f
b10 b
1J
0B
1;
b1000000000 $
b1000000000 G
08
19
#330000
09
#335000
0J
b111010 "
b111010 d
1!
b1 #
b1 c
1`
b0 $
b0 G
0;
b100 e
b10 a
19
#340000
09
#345000
b11 "
b11 d
1!
b0 #
b0 c
0`
b11 b
1_
b111010 @
19
#350000
09
#355000
b0 "
b0 d
0!
1B
b10 D
b100000000 $
b100000000 G
18
b101 :
0_
b11 a
19
#360000
09
#365000
b1 D
19
#370000
09
